psm_analyzer/__init__.py
psm_analyzer/core.py
psm_analyzer-0.1.0.dist-info/METADATA
psm_analyzer-0.1.0.dist-info/WHEEL
psm_analyzer-0.1.0.dist-info/entry_points.txt
psm_analyzer-0.1.0.dist-info/top_level.txt
psm_analyzer-0.1.0.dist-info/RECORD
