Metadata-Version: 2.1
Name: psm-analyzer
Version: 0.1.0
Summary: PSM（Van Westendorp）を計算するPythonツール
Author-email: iwakazusuwa <iwakazusuwa_psm@protonmail.com>
License: MIT
Requires-Python: >=3.8
